{"hierarchy":{"paths":[["doc:\/\/kcswiftui.KCSwiftUI\/documentation\/KCSwiftUI","doc:\/\/kcswiftui.KCSwiftUI\/documentation\/KCSwiftUI\/TimeCell"]]},"kind":"symbol","primaryContentSections":[{"declarations":[{"languages":["swift"],"tokens":[{"text":"nonisolated","kind":"attribute"},{"text":" ","kind":"text"},{"text":"func","kind":"keyword"},{"text":" ","kind":"text"},{"text":"searchable","kind":"identifier"},{"text":"<","kind":"text"},{"text":"C","kind":"genericParameter"},{"text":", ","kind":"text"},{"text":"T","kind":"genericParameter"},{"text":">(","kind":"text"},{"text":"text","kind":"externalParam"},{"text":": ","kind":"text"},{"text":"Binding","preciseIdentifier":"s:7SwiftUI7BindingV","kind":"typeIdentifier"},{"text":"<","kind":"text"},{"text":"String","preciseIdentifier":"s:SS","kind":"typeIdentifier"},{"text":">, ","kind":"text"},{"text":"tokens","kind":"externalParam"},{"text":": ","kind":"text"},{"text":"Binding","preciseIdentifier":"s:7SwiftUI7BindingV","kind":"typeIdentifier"},{"text":"<","kind":"text"},{"text":"C","kind":"typeIdentifier"},{"kind":"text","text":">, "},{"kind":"externalParam","text":"suggestedTokens"},{"kind":"text","text":": "},{"kind":"typeIdentifier","text":"Binding","preciseIdentifier":"s:7SwiftUI7BindingV"},{"kind":"text","text":"<"},{"kind":"typeIdentifier","text":"C"},{"kind":"text","text":">, "},{"kind":"externalParam","text":"placement"},{"kind":"text","text":": "},{"kind":"typeIdentifier","text":"SearchFieldPlacement","preciseIdentifier":"s:7SwiftUI20SearchFieldPlacementV"},{"kind":"text","text":" = .automatic, "},{"kind":"externalParam","text":"prompt"},{"kind":"text","text":": "},{"kind":"typeIdentifier","text":"LocalizedStringKey","preciseIdentifier":"s:7SwiftUI18LocalizedStringKeyV"},{"kind":"text","text":", "},{"kind":"attribute","text":"@"},{"kind":"attribute","text":"ViewBuilder","preciseIdentifier":"s:7SwiftUI11ViewBuilderV"},{"kind":"text","text":" "},{"kind":"externalParam","text":"token"},{"kind":"text","text":": "},{"kind":"keyword","text":"@escaping"},{"kind":"text","text":" ("},{"kind":"typeIdentifier","text":"C"},{"kind":"text","text":"."},{"preciseIdentifier":"s:ST7ElementQa","kind":"typeIdentifier","text":"Element"},{"kind":"text","text":") -> "},{"kind":"typeIdentifier","text":"T"},{"kind":"text","text":") -> "},{"kind":"keyword","text":"some"},{"kind":"text","text":" "},{"preciseIdentifier":"s:7SwiftUI4ViewP","kind":"typeIdentifier","text":"View"},{"kind":"text","text":" "},{"kind":"keyword","text":"where"},{"kind":"text","text":" "},{"kind":"typeIdentifier","text":"C"},{"kind":"text","text":" : "},{"preciseIdentifier":"s:SM","kind":"typeIdentifier","text":"MutableCollection"},{"kind":"text","text":", "},{"kind":"typeIdentifier","text":"C"},{"kind":"text","text":" : "},{"preciseIdentifier":"s:Sk","kind":"typeIdentifier","text":"RandomAccessCollection"},{"kind":"text","text":", "},{"kind":"typeIdentifier","text":"C"},{"kind":"text","text":" : "},{"preciseIdentifier":"s:Sm","kind":"typeIdentifier","text":"RangeReplaceableCollection"},{"kind":"text","text":", "},{"kind":"typeIdentifier","text":"T"},{"kind":"text","text":" : "},{"preciseIdentifier":"s:7SwiftUI4ViewP","kind":"typeIdentifier","text":"View"},{"kind":"text","text":", "},{"kind":"typeIdentifier","text":"C"},{"kind":"text","text":"."},{"preciseIdentifier":"s:ST7ElementQa","kind":"typeIdentifier","text":"Element"},{"kind":"text","text":" : "},{"preciseIdentifier":"s:s12IdentifiableP","kind":"typeIdentifier","text":"Identifiable"},{"kind":"text","text":"\n"}],"platforms":["macOS"]}],"kind":"declarations"}],"variants":[{"paths":["\/documentation\/kcswiftui\/timecell\/searchable(text:tokens:suggestedtokens:placement:prompt:token:)-3a39h"],"traits":[{"interfaceLanguage":"swift"}]}],"abstract":[{"type":"text","text":"Inherited from "},{"type":"codeVoice","code":"View.searchable(text:tokens:suggestedTokens:placement:prompt:token:)"},{"type":"text","text":"."}],"schemaVersion":{"major":0,"minor":3,"patch":0},"sections":[],"metadata":{"title":"searchable(text:tokens:suggestedTokens:placement:prompt:token:)","symbolKind":"method","fragments":[{"text":"func","kind":"keyword"},{"text":" ","kind":"text"},{"text":"searchable","kind":"identifier"},{"text":"<","kind":"text"},{"text":"C","kind":"genericParameter"},{"text":", ","kind":"text"},{"text":"T","kind":"genericParameter"},{"text":">(","kind":"text"},{"text":"text","kind":"externalParam"},{"text":": ","kind":"text"},{"preciseIdentifier":"s:7SwiftUI7BindingV","text":"Binding","kind":"typeIdentifier"},{"text":"<","kind":"text"},{"preciseIdentifier":"s:SS","text":"String","kind":"typeIdentifier"},{"text":">, ","kind":"text"},{"text":"tokens","kind":"externalParam"},{"text":": ","kind":"text"},{"preciseIdentifier":"s:7SwiftUI7BindingV","text":"Binding","kind":"typeIdentifier"},{"text":"<","kind":"text"},{"text":"C","kind":"typeIdentifier"},{"text":">, ","kind":"text"},{"text":"suggestedTokens","kind":"externalParam"},{"kind":"text","text":": "},{"kind":"typeIdentifier","text":"Binding","preciseIdentifier":"s:7SwiftUI7BindingV"},{"kind":"text","text":"<"},{"kind":"typeIdentifier","text":"C"},{"kind":"text","text":">, "},{"kind":"externalParam","text":"placement"},{"kind":"text","text":": "},{"kind":"typeIdentifier","text":"SearchFieldPlacement","preciseIdentifier":"s:7SwiftUI20SearchFieldPlacementV"},{"kind":"text","text":", "},{"kind":"externalParam","text":"prompt"},{"kind":"text","text":": "},{"kind":"typeIdentifier","text":"LocalizedStringKey","preciseIdentifier":"s:7SwiftUI18LocalizedStringKeyV"},{"kind":"text","text":", "},{"kind":"externalParam","text":"token"},{"kind":"text","text":": ("},{"kind":"typeIdentifier","text":"C"},{"kind":"text","text":"."},{"kind":"typeIdentifier","text":"Element","preciseIdentifier":"s:ST7ElementQa"},{"kind":"text","text":") -> "},{"kind":"typeIdentifier","text":"T"},{"text":") -> ","kind":"text"},{"text":"some","kind":"keyword"},{"text":" ","kind":"text"},{"text":"View","kind":"typeIdentifier","preciseIdentifier":"s:7SwiftUI4ViewP"}],"externalID":"s:7SwiftUI4ViewPAAE10searchable4text6tokens15suggestedTokens9placement6prompt5tokenQrAA7BindingVySSG_ALyqd__GAnA20SearchFieldPlacementVAA18LocalizedStringKeyVqd_0_7ElementSTQyd__ctSMRd__SkRd__SmRd__AaBRd_0_s12IdentifiableATRQr0_lF::SYNTHESIZED::s:9KCSwiftUI8TimeCellV","modules":[{"name":"KCSwiftUI","relatedModules":["SwiftUICore"]}],"platforms":[{"beta":false,"name":"iOS","deprecated":false,"introducedAt":"16.0","unavailable":false},{"beta":false,"name":"macOS","deprecated":false,"introducedAt":"13.0","unavailable":false}],"role":"symbol","roleHeading":"Instance Method","extendedModule":"SwiftUICore"},"identifier":{"url":"doc:\/\/kcswiftui.KCSwiftUI\/documentation\/KCSwiftUI\/TimeCell\/searchable(text:tokens:suggestedTokens:placement:prompt:token:)-3a39h","interfaceLanguage":"swift"},"references":{"doc://kcswiftui.KCSwiftUI/documentation/KCSwiftUI/TimeCell":{"kind":"symbol","fragments":[{"kind":"keyword","text":"struct"},{"kind":"text","text":" "},{"kind":"identifier","text":"TimeCell"}],"identifier":"doc:\/\/kcswiftui.KCSwiftUI\/documentation\/KCSwiftUI\/TimeCell","url":"\/documentation\/kcswiftui\/timecell","title":"TimeCell","abstract":[{"type":"text","text":"A cell control for displaying and editing time intervals with platform-specific behavior."}],"role":"symbol","navigatorTitle":[{"kind":"identifier","text":"TimeCell"}],"type":"topic"},"doc://kcswiftui.KCSwiftUI/documentation/KCSwiftUI":{"kind":"symbol","title":"KCSwiftUI","type":"topic","role":"collection","url":"\/documentation\/kcswiftui","identifier":"doc:\/\/kcswiftui.KCSwiftUI\/documentation\/KCSwiftUI","abstract":[]},"doc://kcswiftui.KCSwiftUI/documentation/KCSwiftUI/TimeCell/searchable(text:tokens:suggestedTokens:placement:prompt:token:)-3a39h":{"title":"searchable(text:tokens:suggestedTokens:placement:prompt:token:)","kind":"symbol","type":"topic","abstract":[],"role":"symbol","url":"\/documentation\/kcswiftui\/timecell\/searchable(text:tokens:suggestedtokens:placement:prompt:token:)-3a39h","fragments":[{"text":"func","kind":"keyword"},{"text":" ","kind":"text"},{"text":"searchable","kind":"identifier"},{"text":"<","kind":"text"},{"text":"C","kind":"genericParameter"},{"text":", ","kind":"text"},{"text":"T","kind":"genericParameter"},{"text":">(","kind":"text"},{"text":"text","kind":"externalParam"},{"text":": ","kind":"text"},{"text":"Binding","kind":"typeIdentifier","preciseIdentifier":"s:7SwiftUI7BindingV"},{"text":"<","kind":"text"},{"text":"String","kind":"typeIdentifier","preciseIdentifier":"s:SS"},{"text":">, ","kind":"text"},{"text":"tokens","kind":"externalParam"},{"text":": ","kind":"text"},{"text":"Binding","kind":"typeIdentifier","preciseIdentifier":"s:7SwiftUI7BindingV"},{"text":"<","kind":"text"},{"text":"C","kind":"typeIdentifier"},{"text":">, ","kind":"text"},{"text":"suggestedTokens","kind":"externalParam"},{"kind":"text","text":": "},{"kind":"typeIdentifier","text":"Binding","preciseIdentifier":"s:7SwiftUI7BindingV"},{"kind":"text","text":"<"},{"kind":"typeIdentifier","text":"C"},{"kind":"text","text":">, "},{"kind":"externalParam","text":"placement"},{"kind":"text","text":": "},{"kind":"typeIdentifier","text":"SearchFieldPlacement","preciseIdentifier":"s:7SwiftUI20SearchFieldPlacementV"},{"kind":"text","text":", "},{"kind":"externalParam","text":"prompt"},{"kind":"text","text":": "},{"kind":"typeIdentifier","text":"LocalizedStringKey","preciseIdentifier":"s:7SwiftUI18LocalizedStringKeyV"},{"kind":"text","text":", "},{"kind":"externalParam","text":"token"},{"kind":"text","text":": ("},{"kind":"typeIdentifier","text":"C"},{"kind":"text","text":"."},{"kind":"typeIdentifier","text":"Element","preciseIdentifier":"s:ST7ElementQa"},{"kind":"text","text":") -> "},{"kind":"typeIdentifier","text":"T"},{"text":") -> ","kind":"text"},{"text":"some","kind":"keyword"},{"text":" ","kind":"text"},{"text":"View","preciseIdentifier":"s:7SwiftUI4ViewP","kind":"typeIdentifier"}],"identifier":"doc:\/\/kcswiftui.KCSwiftUI\/documentation\/KCSwiftUI\/TimeCell\/searchable(text:tokens:suggestedTokens:placement:prompt:token:)-3a39h"}}}